{
  "currency": "BRL",
  "language": "Idioma",

  "add-to-cart": "Adicionar ao carrinho",
  "description": "Descrição",

  "home": {
    "title": "Iníco"
  },

  "checkout": {
    "shipment": {
      "title": "Dados do envio",
      "personal_info": "Dados pessoais",
      "shipment_address": "Endereço de entrega",
      "first_name": "Nome",
      "last_name": "Sobrenome",
      "address": "Endereço",
      "city": "Cidade",
      "state_province": "Estado",
      "country": "País",
      "postal_code": "CEP",
      "email": "E-mail",
      "next_button": "Avançar",
      "cart_is_empty": "Seu carrinho de compras está vazio.",
      "back_to_home": "Voltar para a página inicial"
    },
    "payment": {
      "title": "Pagamento"
    }
  },

  "cart": {
    "cart_is_empty": "O carrinho está vazio.",
    "shopping_cart": "Carrinho de compras",
    "proceed_to_checkout": "Finalizar compra"
  },

  "products": {
    "CPTR1912": {
      "name": "Cartão postal \"Travessia\"",
      "slug": "cartao-postal-travessia",
      "description": "Lorem ipsum dolor sit amet, consectetur adipiscing elit. Quisque vehicula vestibulum nibh. Mauris in metus nisi. Duis accumsan blandit metus quis imperdiet. Nulla eu ipsum eu quam interdum interdum non eget augue. Donec nec libero sollicitudin, aliquet nisl in, vulputate mi. Nulla facilisi. Cras ut ipsum et justo auctor gravida ut in dui."
    },
    "CPTS1912": {
      "name": "Cartão postal \"Transeuntes\"",
      "slug": "cartao-postal-transeuntes",
      "description": "Lorem ipsum dolor sit amet, consectetur adipiscing elit. Quisque vehicula vestibulum nibh. Mauris in metus nisi. Duis accumsan blandit metus quis imperdiet. Nulla eu ipsum eu quam interdum interdum non eget augue. Donec nec libero sollicitudin, aliquet nisl in, vulputate mi. Nulla facilisi. Cras ut ipsum et justo auctor gravida ut in dui."
    }
  }
}